{
  "lecture_no": 4,
  "selected": [
    {
      "video_id": "mFFXuXjVgkU",
      "title": "Github Actions CI/CD - Everything you need to know to get started",
      "url": "https://www.youtube.com/watch?v=mFFXuXjVgkU",
      "channel": "DevOps Journey",
      "duration_sec": 741,
      "has_subtitle": true,
      "subtitle_lang": "en",
      "score": 0.91,
      "reason": "396K 조회수·12분 적정 분량·입문자 대상 GitHub Actions CI 파이프라인 전체 흐름 커버, 자막 자동생성(영어)"
    },
    {
      "video_id": "MIWH2CpVyXs",
      "title": "The ONLY Continuous Integration (CI) Tutorial you need as an Engineer",
      "url": "https://www.youtube.com/watch?v=MIWH2CpVyXs",
      "channel": "TechWorld with Nana",
      "duration_sec": 1705,
      "has_subtitle": true,
      "subtitle_lang": "en",
      "score": 0.88,
      "reason": "CI 개념·빌드·테스트 자동화 전용 튜토리얼, 127K 조회수, TechWorld with Nana 고신뢰 채널, 자막 자동생성(영어)"
    },
    {
      "video_id": "sIPU_VkrguI",
      "title": "[10분 테코톡] 찬, 레넌의 CI/CD와 무중단 배포",
      "url": "https://www.youtube.com/watch?v=sIPU_VkrguI",
      "channel": "우아한테크",
      "duration_sec": 944,
      "has_subtitle": true,
      "subtitle_lang": "ko",
      "score": 0.82,
      "reason": "한국어 수동 자막, 우아한테크 고신뢰 채널, 15분 분량으로 CI/CD 흐름 전반을 한국어로 설명"
    }
  ],
  "note": "YouTube Data API 할당량 초과로 yt-dlp fallback 검색 사용. search_max_age_years=5 적용(커리큘럼 지정값). 영어 자막 영상 2개·한국어 자막 영상 1개 선정."
}
