[
  {
    "video_id": "TlHvYWVUZyc",
    "title": "Kubernetes Explained in 6 Minutes | k8s Architecture",
    "channel": "ByteByteGo",
    "published": "2023-01-11T16:41:34Z",
    "duration_iso": "PT6M28S",
    "caption_flag": true,
    "views": 1732470,
    "likes": 34508,
    "url": "https://www.youtube.com/watch?v=TlHvYWVUZyc",
    "duration_sec": 388
  },
  {
    "video_id": "VQUZF6k6g88",
    "title": "Kubernetes architecture: Nodes and control plane",
    "channel": "Google Cloud Tech",
    "published": "2020-12-06T00:00:04Z",
    "duration_iso": "PT4M3S",
    "caption_flag": true,
    "views": 73910,
    "likes": 1238,
    "url": "https://www.youtube.com/watch?v=VQUZF6k6g88",
    "duration_sec": 243
  },
  {
    "video_id": "XB_5BFbTYMA",
    "title": "Kubernetes Architecture Explained — Lesson 01 (Control Plane + Workers)",
    "channel": "Dargslan",
    "published": "2026-04-29T13:58:57Z",
    "duration_iso": "PT9M10S",
    "caption_flag": true,
    "views": 9,
    "likes": 0,
    "url": "https://www.youtube.com/watch?v=XB_5BFbTYMA",
    "duration_sec": 550
  },
  {
    "video_id": "daVUONZqn88",
    "title": "How Kubernetes works",
    "channel": "Microsoft Azure",
    "published": "2019-02-19T19:05:52Z",
    "duration_iso": "PT5M35S",
    "caption_flag": true,
    "views": 303284,
    "likes": 3638,
    "url": "https://www.youtube.com/watch?v=daVUONZqn88",
    "duration_sec": 335
  },
  {
    "video_id": "Ucj4HT78lUA",
    "title": "Kubernetes cluster management made easy | CloudWorld 2022",
    "channel": "Oracle",
    "published": "2022-11-28T15:00:29Z",
    "duration_iso": "PT29M43S",
    "caption_flag": true,
    "views": 515,
    "likes": 6,
    "url": "https://www.youtube.com/watch?v=Ucj4HT78lUA",
    "duration_sec": 1783
  },
  {
    "video_id": "syBe1H-qe8U",
    "title": "A Quick Tour of Kubernetes on Oracle Linux",
    "channel": "Oracle Learning",
    "published": "2022-03-25T12:01:41Z",
    "duration_iso": "PT6M36S",
    "caption_flag": true,
    "views": 1868,
    "likes": 20,
    "url": "https://www.youtube.com/watch?v=syBe1H-qe8U",
    "duration_sec": 396
  },
  {
    "video_id": "B_X4l4HSgtc",
    "title": "Kubernetes Basics: Pods, Nodes, Containers, Deployments and Clusters",
    "channel": "Anton Putra",
    "published": "2021-11-17T10:00:54Z",
    "duration_iso": "PT5M54S",
    "caption_flag": true,
    "views": 130018,
    "likes": 2081,
    "url": "https://www.youtube.com/watch?v=B_X4l4HSgtc",
    "duration_sec": 354
  },
  {
    "video_id": "iiSKclYuLCs",
    "title": "Cloud Native for Beginners: The Kubernetes Components",
    "channel": "SAP Developers",
    "published": "2022-03-23T16:00:53Z",
    "duration_iso": "PT2M10S",
    "caption_flag": true,
    "views": 1597,
    "likes": 32,
    "url": "https://www.youtube.com/watch?v=iiSKclYuLCs",
    "duration_sec": 130
  },
  {
    "video_id": "vZ9gEqeddxQ",
    "title": "Day 2 | Kubernetes Architecture explained",
    "channel": "Raghav Dua",
    "published": "2024-02-14T02:45:02Z",
    "duration_iso": "PT10M3S",
    "caption_flag": true,
    "views": 6499,
    "likes": 256,
    "url": "https://www.youtube.com/watch?v=vZ9gEqeddxQ",
    "duration_sec": 603
  },
  {
    "video_id": "hsJ2qtwoWZw",
    "title": "Kubernetes Autoscaling: HPA vs. VPA vs. Keda vs. CA vs. Karpenter vs. Fargate",
    "channel": "Anton Putra",
    "published": "2023-11-19T10:44:29Z",
    "duration_iso": "PT14M38S",
    "caption_flag": true,
    "views": 56532,
    "likes": 1644,
    "url": "https://www.youtube.com/watch?v=hsJ2qtwoWZw",
    "duration_sec": 878
  },
  {
    "video_id": "l8ZV3xkcF1o",
    "title": "Main Components of Kubernetes.",
    "channel": "Cuemby",
    "published": "2020-01-11T04:56:10Z",
    "duration_iso": "PT5M35S",
    "caption_flag": true,
    "views": 297,
    "likes": 6,
    "url": "https://www.youtube.com/watch?v=l8ZV3xkcF1o",
    "duration_sec": 335
  },
  {
    "video_id": "-1cOmlvrcc0",
    "title": "Kubernetes Architecture Explained | Simple Breakdown for Beginners",
    "channel": "GRITTOCODES",
    "published": "2024-12-14T18:41:43Z",
    "duration_iso": "PT3M31S",
    "caption_flag": true,
    "views": 110,
    "likes": 3,
    "url": "https://www.youtube.com/watch?v=-1cOmlvrcc0",
    "duration_sec": 211
  },
  {
    "video_id": "9_D9earLQho",
    "title": "AKS Control Plane vs Worker Nodes Explained (Azure Tutorial)",
    "channel": "TechSpark Studio",
    "published": "2025-10-02T16:00:06Z",
    "duration_iso": "PT8M35S",
    "caption_flag": true,
    "views": 150,
    "likes": 6,
    "url": "https://www.youtube.com/watch?v=9_D9earLQho",
    "duration_sec": 515
  },
  {
    "video_id": "TxnCMhYhqRU",
    "title": "[Backend #30] Kubernetes architecture & How to create an EKS cluster on AWS",
    "channel": "TECH SCHOOL",
    "published": "2021-08-01T16:52:00Z",
    "duration_iso": "PT17M28S",
    "caption_flag": true,
    "views": 11512,
    "likes": 227,
    "url": "https://www.youtube.com/watch?v=TxnCMhYhqRU",
    "duration_sec": 1048
  },
  {
    "video_id": "ThCD-IZpPdk",
    "title": "Introduction to Kubernetes",
    "channel": "LearnCantrill",
    "published": "2022-08-10T00:30:04Z",
    "duration_iso": "PT11M28S",
    "caption_flag": true,
    "views": 7859,
    "likes": 228,
    "url": "https://www.youtube.com/watch?v=ThCD-IZpPdk",
    "duration_sec": 688
  },
  {
    "video_id": "eRfHp16qJq8",
    "title": "개발자를 위한 쉬운 도커 (2024 NEW) | 컨테이너, 도커, 쿠버네티스의 개념을 엄청 쉽게 알려드려요.",
    "channel": "인프런 inflearn",
    "published": "2024-01-16T08:00:17Z",
    "duration_iso": "PT7M28S",
    "caption_flag": true,
    "views": 67491,
    "likes": 1897,
    "url": "https://www.youtube.com/watch?v=eRfHp16qJq8",
    "duration_sec": 448
  },
  {
    "video_id": "S8eX0MxfnB4",
    "title": "Kubernetes Roadmap - Complete Step-by-Step Learning Path",
    "channel": "TechWorld with Nana",
    "published": "2023-08-09T14:07:05Z",
    "duration_iso": "PT26M58S",
    "caption_flag": true,
    "views": 287452,
    "likes": 6376,
    "url": "https://www.youtube.com/watch?v=S8eX0MxfnB4",
    "duration_sec": 1618
  },
  {
    "video_id": "aSrqRSk43lY",
    "title": "Kubernetes Explained",
    "channel": "IBM Technology",
    "published": "2019-03-08T20:58:10Z",
    "duration_iso": "PT10M59S",
    "caption_flag": true,
    "views": 702381,
    "likes": 11909,
    "url": "https://www.youtube.com/watch?v=aSrqRSk43lY",
    "duration_sec": 659
  },
  {
    "video_id": "Cvcj4bbaOUo",
    "title": "🐳 도커, 컨테이너, 쿠버네티스! 처음이신분들은 한 번씩 보고 가세요! !! 초보자 가이드!! (docker, container, kubernates) 🚀",
    "channel": "Byte Pancake",
    "published": "2024-03-31T23:00:05Z",
    "duration_iso": "PT8M",
    "caption_flag": true,
    "views": 6867,
    "likes": 166,
    "url": "https://www.youtube.com/watch?v=Cvcj4bbaOUo",
    "duration_sec": 480
  },
  {
    "video_id": "6IPu3WU_M0o",
    "title": "Kubernetes Basics: Pods, Nodes, Containers, Deployments & Clusters",
    "channel": "Anton Putra",
    "published": "2023-07-04T03:35:06Z",
    "duration_iso": "PT8M6S",
    "caption_flag": true,
    "views": 68550,
    "likes": 1437,
    "url": "https://www.youtube.com/watch?v=6IPu3WU_M0o",
    "duration_sec": 486
  },
  {
    "video_id": "lv0DdVLZuHc",
    "title": "Why is Kubernetes Popular | What is Kubernetes?",
    "channel": "ByteByteGo",
    "published": "2024-10-08T15:30:18Z",
    "duration_iso": "PT9M52S",
    "caption_flag": true,
    "views": 128156,
    "likes": 3935,
    "url": "https://www.youtube.com/watch?v=lv0DdVLZuHc",
    "duration_sec": 592
  }
]