{
  "lecture_no": 8,
  "selected": [
    {
      "video_id": "UMQGyeAnfFE",
      "title": "10 DevOps Tools you need to know - The Complete Guide",
      "url": "https://www.youtube.com/watch?v=UMQGyeAnfFE",
      "channel": "TechWorld with Nana",
      "duration_sec": 687,
      "has_subtitle": true,
      "subtitle_lang": "en",
      "score": 0.89,
      "reason": "DevOps 핵심 도구 10종(Git, Docker, Kubernetes, Jenkins, Terraform 등)을 체계적으로 설명하는 영상. TechWorld with Nana는 DevOps 교육 채널 중 신뢰도가 가장 높으며 영어 수동 자막 제공. 이 강의의 '도구 생태계 한눈에 보기' 목표에 가장 직접적으로 부합하며 11분 길이로 핵심 전달에 적합."
    },
    {
      "video_id": "6GQRb4fGvtk",
      "title": "The Complete DevOps Roadmap",
      "url": "https://www.youtube.com/watch?v=6GQRb4fGvtk",
      "channel": "Programming with Mosh",
      "duration_sec": 481,
      "has_subtitle": true,
      "subtitle_lang": "en",
      "score": 0.86,
      "reason": "DevOps 학습 로드맵을 단계별로 안내하는 영상. Programming with Mosh는 신뢰도 높은 기술 교육 채널로 조회수 59만을 기록. 입문 이후 학습 방향 제시라는 강의 목표에 부합하며 8분 길이로 앞 영상과 합산 19분 분량을 채움."
    },
    {
      "video_id": "eRfHp16qJq8",
      "title": "개발자를 위한 쉬운 도커 (2024 NEW) | 컨테이너, 도커, 쿠버네티스의 개념을 엄청 쉽게 알려드려요.",
      "url": "https://www.youtube.com/watch?v=eRfHp16qJq8",
      "channel": "인프런 inflearn",
      "duration_sec": 448,
      "has_subtitle": true,
      "subtitle_lang": "ko",
      "score": 0.82,
      "reason": "컨테이너·Docker·Kubernetes 개념을 한국어로 쉽게 설명하는 2024년 영상. 인프런은 국내 최대 개발자 교육 플랫폼으로 채널 신뢰도가 높음. 한국어 수동 자막 제공으로 한국어 페이지 출처 영상으로 활용. 컨테이너가 DevOps에서 왜 중요한지 설명하는 강의 첫 번째 목표에 부합."
    }
  ],
  "note": "YouTube Data API 할당량 초과로 yt-dlp fallback 사용. search_max_age_years=5 적용. 한국어 자막 영상(eRfHp16qJq8)은 'docker container 입문' 키워드 추가 검색으로 확보. 영어 자막 영상 2개(UMQGyeAnfFE, 6GQRb4fGvtk)와 한국어 자막 영상 1개(eRfHp16qJq8) 포함."
}
