{
  "query": "kubernetes taints tolerations",
  "videos": [
    {
      "video_id": "rX4v_L0k4Hc",
      "title": "Kubernetes Node Selector vs Node Affinity vs Pod Affinity vs Tains & Tolerations",
      "channel": "Anton Putra",
      "published": "2023-07-29T03:44:15Z",
      "duration_iso": "PT11M17S",
      "caption_flag": true,
      "views": 54150,
      "likes": 1219,
      "url": "https://www.youtube.com/watch?v=rX4v_L0k4Hc"
    },
    {
      "video_id": "6EMtEJC00FY",
      "title": "Kubernetes Taints and Tolerations (Examples)",
      "channel": "Anton Putra",
      "published": "2021-12-01T10:00:06Z",
      "duration_iso": "PT3M11S",
      "caption_flag": true,
      "views": 7718,
      "likes": 97,
      "url": "https://www.youtube.com/watch?v=6EMtEJC00FY"
    },
    {
      "video_id": "DKLMzDD3xqA",
      "title": "Kubernetes Affinity and Anti Affinity vs NodeSelector (Examples)",
      "channel": "Anton Putra",
      "published": "2021-11-29T10:00:06Z",
      "duration_iso": "PT5M22S",
      "caption_flag": true,
      "views": 16807,
      "likes": 280,
      "url": "https://www.youtube.com/watch?v=DKLMzDD3xqA"
    },
    {
      "video_id": "PwlO_2rxoKk",
      "title": "Taints in Kubernetes",
      "channel": "DEVOPS TRAINING BY PREETHI DOVALA",
      "published": "2023-06-10T11:40:09Z",
      "duration_iso": "PT45S",
      "caption_flag": true,
      "views": 1236,
      "likes": 14,
      "url": "https://www.youtube.com/watch?v=PwlO_2rxoKk"
    },
    {
      "video_id": "rwOVCMeBcAs",
      "title": "Troubleshooting Kubernetes using AI | CrashloopBackoff, Node Affinity, Taints & Tolerations",
      "channel": "Raghav Dua",
      "published": "2024-09-13T08:45:04Z",
      "duration_iso": "PT36M12S",
      "caption_flag": true,
      "views": 1899,
      "likes": 91,
      "url": "https://www.youtube.com/watch?v=rwOVCMeBcAs"
    },
    {
      "video_id": "TlHvYWVUZyc",
      "title": "Kubernetes Explained in 6 Minutes | k8s Architecture",
      "channel": "ByteByteGo",
      "published": "2023-01-11T16:41:34Z",
      "duration_iso": "PT6M28S",
      "caption_flag": true,
      "views": 1732616,
      "likes": 34512,
      "url": "https://www.youtube.com/watch?v=TlHvYWVUZyc"
    },
    {
      "video_id": "sR_Zmvme3-0",
      "title": "Kubernetes Pod Priority (Examples)",
      "channel": "Anton Putra",
      "published": "2021-11-24T10:15:03Z",
      "duration_iso": "PT2M22S",
      "caption_flag": true,
      "views": 5147,
      "likes": 110,
      "url": "https://www.youtube.com/watch?v=sR_Zmvme3-0"
    },
    {
      "video_id": "30KAInyvY_o",
      "title": "Kubernetes Deployment vs. StatefulSet vs. DaemonSet",
      "channel": "Anton Putra",
      "published": "2023-07-10T04:22:27Z",
      "duration_iso": "PT6M43S",
      "caption_flag": true,
      "views": 76997,
      "likes": 1942,
      "url": "https://www.youtube.com/watch?v=30KAInyvY_o"
    },
    {
      "video_id": "rDCWxkvPlAw",
      "title": "How the Kubernetes scheduler works",
      "channel": "Microsoft Azure",
      "published": "2019-02-19T19:06:09Z",
      "duration_iso": "PT7M35S",
      "caption_flag": true,
      "views": 73596,
      "likes": 845,
      "url": "https://www.youtube.com/watch?v=rDCWxkvPlAw"
    },
    {
      "video_id": "AzFtT_yOQ-8",
      "title": "kubernetes начало [DaemonSet, Taints, NodeSelector] [2025]",
      "channel": "Артур Крюков",
      "published": "2025-11-07T07:00:06Z",
      "duration_iso": "PT24M48S",
      "caption_flag": true,
      "views": 2136,
      "likes": 103,
      "url": "https://www.youtube.com/watch?v=AzFtT_yOQ-8"
    },
    {
      "video_id": "ji7mXjyR3v0",
      "title": "Kubernetes Taints and Tolerations: Why Most DevOps Teams Get This Wrong?",
      "channel": "Techi Nik",
      "published": "2025-07-22T08:10:37Z",
      "duration_iso": "PT8M23S",
      "caption_flag": true,
      "views": 111,
      "likes": 2,
      "url": "https://www.youtube.com/watch?v=ji7mXjyR3v0"
    },
    {
      "video_id": "FDDMh2yBrLg",
      "title": "Decision Microservices in Kubernetes",
      "channel": "Trisotech",
      "published": "2021-04-22T19:20:19Z",
      "duration_iso": "PT24M54S",
      "caption_flag": true,
      "views": 139,
      "likes": 4,
      "url": "https://www.youtube.com/watch?v=FDDMh2yBrLg"
    },
    {
      "video_id": "ka-HItczp2I",
      "title": "Kubernetes Quality of Service (QoS) Classes for Pods (Guaranteed, Burstable, BestEffort)",
      "channel": "Anton Putra",
      "published": "2021-11-22T10:00:17Z",
      "duration_iso": "PT2M58S",
      "caption_flag": true,
      "views": 4789,
      "likes": 159,
      "url": "https://www.youtube.com/watch?v=ka-HItczp2I"
    },
    {
      "video_id": "12I7UwT7xXQ",
      "title": "Understanding Kubernetes in a visual way - 16 - Nodes (Cordon, Drain,Taint) | Kubernetes en français",
      "channel": "Aurelie Vache",
      "published": "2021-06-13T13:39:33Z",
      "duration_iso": "PT3M28S",
      "caption_flag": true,
      "views": 704,
      "likes": 22,
      "url": "https://www.youtube.com/watch?v=12I7UwT7xXQ"
    },
    {
      "video_id": "G3R24JSlGjY",
      "title": "Understand Role Based Access Control in Kubernetes",
      "channel": "Microsoft Azure",
      "published": "2019-05-09T16:10:30Z",
      "duration_iso": "PT7M15S",
      "caption_flag": true,
      "views": 54137,
      "likes": 655,
      "url": "https://www.youtube.com/watch?v=G3R24JSlGjY"
    }
  ]
}