[
  {
    "video_id": "plB3kyZLHe8",
    "title": "Namespaces in Kubernetes",
    "channel": "Google Cloud Tech",
    "published": "2021-07-02T16:00:35Z",
    "duration_iso": "PT5M32S",
    "duration_sec": 332,
    "views": 34951,
    "likes": 573,
    "url": "https://www.youtube.com/watch?v=plB3kyZLHe8"
  },
  {
    "video_id": "tyoaLuaVyuQ",
    "title": "Kubernetes LimitRange Explained | Default Resource Limits & Requests + Resource Quota Demo",
    "channel": "Techi Nik",
    "published": "2025-07-01T05:55:52Z",
    "duration_iso": "PT7M58S",
    "duration_sec": 478,
    "views": 455,
    "likes": 11,
    "url": "https://www.youtube.com/watch?v=tyoaLuaVyuQ"
  },
  {
    "video_id": "dYLRW0DZVGk",
    "title": "What Happens When You Don't Use Kubernetes Resource Quotas?",
    "channel": "Techi Nik",
    "published": "2025-06-24T08:18:08Z",
    "duration_iso": "PT6M10S",
    "duration_sec": 370,
    "views": 313,
    "likes": 15,
    "url": "https://www.youtube.com/watch?v=dYLRW0DZVGk"
  },
  {
    "video_id": "2CrprvnzPXY",
    "title": "Kubernetes CPU Limits & Requests EXPLAINED (Stop Wasting Resources!)",
    "channel": "Alta3 Research",
    "published": "2025-03-19T13:00:08Z",
    "duration_iso": "PT4M39S",
    "duration_sec": 279,
    "views": 3593,
    "likes": 74,
    "url": "https://www.youtube.com/watch?v=2CrprvnzPXY"
  },
  {
    "video_id": "IuxusQKHWR0",
    "title": "Kubernetes Namespaces Explained with Hands-on Demo | Isolate Resources Like a Pro",
    "channel": "Techi Nik",
    "published": "2025-06-03T08:18:25Z",
    "duration_iso": "PT8M22S",
    "duration_sec": 502,
    "views": 278,
    "likes": 11,
    "url": "https://www.youtube.com/watch?v=IuxusQKHWR0"
  },
  {
    "video_id": "IP64cimwwgM",
    "title": "Kubernetes Namespaces vs. Virtual Clusters",
    "channel": "Anton Putra",
    "published": "2021-11-15T10:00:06Z",
    "duration_iso": "PT6M47S",
    "duration_sec": 407,
    "views": 5043,
    "likes": 101,
    "url": "https://www.youtube.com/watch?v=IP64cimwwgM"
  },
  {
    "video_id": "vDLDIW0A5-c",
    "title": "What is Namespace in Kubernetes?",
    "channel": "devops-wala",
    "published": "2023-01-15T07:06:36Z",
    "duration_iso": "PT17M29S",
    "duration_sec": 1049,
    "views": 1545,
    "likes": 49,
    "url": "https://www.youtube.com/watch?v=vDLDIW0A5-c"
  }
]
